{"0": {"name": "GP@paris.com", "Trust": 0.0, "SpamN": 7644, "HamN": 0, "Date_of_first_seen_message": 1072051200.0, "Date_of_last_seen_message": 1125964800.0, "Groups": ["default"]}, "1": {"name": "BG@paris.com", "Trust": 0.0, "SpamN": 2588, "HamN": 0, "Date_of_first_seen_message": 1092441600.0, "Date_of_last_seen_message": 1122595200.0, "Groups": ["default"]}, "2": {"name": "SA_and_HP@paris.com", "Trust": 0.0, "SpamN": 2320, "HamN": 0, "Date_of_first_seen_message": 994377600.0, "Date_of_last_seen_message": 1121990400.0, "Groups": ["default"]}, "3": {"name": "kitchen@paris.com", "Trust": 100.0, "SpamN": 0, "HamN": 5070, "Date_of_first_seen_message": 981676800.0, "Date_of_last_seen_message": 1012867200.0, "Groups": ["default"]}, "4": {"name": "kaminski@paris.com", "Trust": 100.0, "SpamN": 0, "HamN": 5898, "Date_of_first_seen_message": 947030400.0, "Date_of_last_seen_message": 989539200.0, "Groups": ["default"]}, "5": {"name": "williams@paris.com", "Trust": 100.0, "SpamN": 0, "HamN": 1836, "Date_of_first_seen_message": 992304000.0, "Date_of_last_seen_message": 1012953600.0, "Groups": ["default"]}, "6": {"name": "farmer@paris.com", "Trust": 100.0, "SpamN": 0, "HamN": 4644, "Date_of_first_seen_message": 945129600.0, "Date_of_last_seen_message": 1010620800.0, "Groups": ["default"]}}